{"name":"PushCrateMission","is_setup":false,"is_shutdown":false,"order":1,"steps":[{"step_type":"","function_name":"servo_pom_arm_up","arguments":[],"position":{"x":298,"y":120},"children":[]},{"step_type":"","function_name":"strafe_until_black","arguments":[{"name":"sensor","value":null,"type":"Union[IRSensor, list[IRSensor]]"},{"name":"strafe_speed","value":null,"type":"float"},{"name":"confidence_threshold","value":0.7,"type":"float"}],"position":{"x":344.9999999999991,"y":261.7500000000004},"children":[]}],"comments":[],"groups":[]}